server.py
test_comfyui.py
client/__init__.py
client/comfyui.py
iflow_mcp_overseer66_comfyui_mcp_server-0.1.0.dist-info/licenses/LICENSE
iflow_mcp_overseer66_comfyui_mcp_server-0.1.0.dist-info/METADATA
iflow_mcp_overseer66_comfyui_mcp_server-0.1.0.dist-info/WHEEL
iflow_mcp_overseer66_comfyui_mcp_server-0.1.0.dist-info/entry_points.txt
iflow_mcp_overseer66_comfyui_mcp_server-0.1.0.dist-info/top_level.txt
iflow_mcp_overseer66_comfyui_mcp_server-0.1.0.dist-info/RECORD
