Metadata-Version: 2.4
Name: iflow-mcp_overseer66_comfyui-mcp-server
Version: 0.1.0
Summary: Add your description here
Requires-Python: >=3.11
License-File: LICENSE
Requires-Dist: mcp[cli]>=1.6.0
Requires-Dist: python-dotenv>=1.1.0
Requires-Dist: websocket-client>=1.8.0
Dynamic: license-file
